{"cameraMode":{"drawMode":0,"name":"Shaded","section":"Shading Mode"},"sceneLighting":false,"audioPlay":false,"sceneViewState":{"m_AlwaysRefresh":false,"showFog":true,"showSkybox":false,"showFlares":true,"showImageEffects":true,"showParticleSystems":true,"showVisualEffectGraphs":true,"m_FxEnabled":true},"in2DMode":false,"pivot":{"x":571.370849609375,"y":2.2100648880004885,"z":785.1982421875},"rotation":{"x":0.12027111649513245,"y":-0.6253737807273865,"z":0.09835749864578247,"w":0.7647041082382202},"size":1.0675525665283204,"orthographic":false}